kbackground/__init__.py
kbackground/kbackground.py
kbackground-0.1.9.dist-info/LICENSE
kbackground-0.1.9.dist-info/WHEEL
kbackground-0.1.9.dist-info/METADATA
kbackground-0.1.9.dist-info/RECORD
